jwutils/__init__.py
jwutils/gh.py
jwutils/py.typed
jwutils-0.1.5.dist-info/METADATA
jwutils-0.1.5.dist-info/WHEEL
jwutils-0.1.5.dist-info/RECORD
